MANIFEST.in
README.rst
setup.py
async_keepalive_httpc/VERSION.json
async_keepalive_httpc/__init__.py
async_keepalive_httpc/keepalive_client.py
async_keepalive_httpc/pool.py
async_keepalive_httpc/utils.py
async_keepalive_httpc.egg-info/PKG-INFO
async_keepalive_httpc.egg-info/SOURCES.txt
async_keepalive_httpc.egg-info/dependency_links.txt
async_keepalive_httpc.egg-info/requires.txt
async_keepalive_httpc.egg-info/top_level.txt
async_keepalive_httpc/aws/__init__.py
async_keepalive_httpc/aws/auth.py
async_keepalive_httpc/aws/common.py
async_keepalive_httpc/aws/dynamodb.py
async_keepalive_httpc/aws/kinesis.py
async_keepalive_httpc/aws/sqs.py