Metadata-Version: 1.1
Name: async-keepalive-httpc
Version: 0.15
Summary: An async http client with keep-alive capabilities
Home-page: https://github.com/tly1980/async_keepalive_httpc
Author: Tom Tang
Author-email: tly1980@gmail.com
License: BSD
Platform: any
Classifier: Development Status :: 2 - Pre-Alpha
Classifier: Environment :: Web Environment
Classifier: Intended Audience :: Developers
Classifier: License :: OSI Approved :: BSD License
Classifier: Operating System :: OS Independent
Classifier: Programming Language :: Python
Classifier: Topic :: Internet :: WWW/HTTP :: Dynamic Content
Classifier: Topic :: Software Development :: Libraries :: Python Modules
